lusid_asyncio/__init__.py
lusid_asyncio/__version__.py
lusid_asyncio/api_client.py
lusid_asyncio/configuration.py
lusid_asyncio/exceptions.py
lusid_asyncio/rest.py
lusid_asyncio/api/__init__.py
lusid_asyncio/api/aggregation_api.py
lusid_asyncio/api/allocations_api.py
lusid_asyncio/api/application_metadata_api.py
lusid_asyncio/api/blocks_api.py
lusid_asyncio/api/calendars_api.py
lusid_asyncio/api/complex_market_data_api.py
lusid_asyncio/api/compliance_api.py
lusid_asyncio/api/configuration_recipe_api.py
lusid_asyncio/api/conventions_api.py
lusid_asyncio/api/corporate_action_sources_api.py
lusid_asyncio/api/counterparties_api.py
lusid_asyncio/api/custom_entities_api.py
lusid_asyncio/api/custom_entity_definitions_api.py
lusid_asyncio/api/cut_label_definitions_api.py
lusid_asyncio/api/data_types_api.py
lusid_asyncio/api/derived_transaction_portfolios_api.py
lusid_asyncio/api/entities_api.py
lusid_asyncio/api/executions_api.py
lusid_asyncio/api/fees_and_commissions_api.py
lusid_asyncio/api/instruments_api.py
lusid_asyncio/api/legal_entities_api.py
lusid_asyncio/api/order_graph_api.py
lusid_asyncio/api/order_instructions_api.py
lusid_asyncio/api/orders_api.py
lusid_asyncio/api/packages_api.py
lusid_asyncio/api/participations_api.py
lusid_asyncio/api/persons_api.py
lusid_asyncio/api/placements_api.py
lusid_asyncio/api/portfolio_groups_api.py
lusid_asyncio/api/portfolios_api.py
lusid_asyncio/api/property_definitions_api.py
lusid_asyncio/api/quotes_api.py
lusid_asyncio/api/reconciliations_api.py
lusid_asyncio/api/reference_portfolio_api.py
lusid_asyncio/api/relation_definitions_api.py
lusid_asyncio/api/relations_api.py
lusid_asyncio/api/relationship_definitions_api.py
lusid_asyncio/api/relationships_api.py
lusid_asyncio/api/schemas_api.py
lusid_asyncio/api/scopes_api.py
lusid_asyncio/api/search_api.py
lusid_asyncio/api/sequences_api.py
lusid_asyncio/api/structured_result_data_api.py
lusid_asyncio/api/system_configuration_api.py
lusid_sdk_asyncio_preview-0.11.3923b0.dist-info/METADATA
lusid_sdk_asyncio_preview-0.11.3923b0.dist-info/WHEEL
lusid_sdk_asyncio_preview-0.11.3923b0.dist-info/top_level.txt
lusid_sdk_asyncio_preview-0.11.3923b0.dist-info/RECORD
