Metadata-Version: 2.1
Name: lusid-sdk-asyncio-preview
Version: 0.11.3923b0
Summary: Python Asyncio Preview SDK for LUSID API
Home-page: https://github.com/finbourne/lusid-sdk-python-asyncio-preview
Author: FINBOURNE Technology
Author-email: engineering@finbourne.com
License: MIT
Keywords: OpenAPI,FINBOURNE,LUSID,LUSID API
Platform: UNKNOWN
Requires-Dist: urllib3 (>=1.15)
Requires-Dist: six (>=1.10)
Requires-Dist: certifi (>=14.05.14)
Requires-Dist: python-dateutil (>=2.5.3)
Requires-Dist: urllib3 (>=1.15.1)
Requires-Dist: requests (>=2.21.0)
